compmake_plugins.cpython-310-aarch64-linux-gnu.so
compmake.cpython-310-aarch64-linux-gnu.so
compmake_plugins.pyi
compmake.pyi
compmake_z7-7.3.2201261049.dist-info/METADATA
compmake_z7-7.3.2201261049.dist-info/entry_points.txt
compmake_z7-7.3.2201261049.dist-info/WHEEL
compmake_z7-7.3.2201261049.dist-info/top_level.txt
compmake_z7-7.3.2201261049.dist-info/zip-safe
compmake_z7-7.3.2201261049.dist-info/RECORD
